{
  "fr": {
    "read": "temps de lecture",
    "author" : "Auteur : ",
    "all" : "Tous les articles",
    "fact" : "Fiches pratiques",
    "press" : "Articles de presse",
    "factSingle" : "Fiche pratique",
    "pressSingle" : "Article de presse",
    "source" : "lien vers le site source",
    "only" : "Uniquement en anglais",
    "sorry" : "Désolé, il n'y a pas d'articles dans cette catégorie pour le moment"
  },

  "en": {
    "read": "read time",
    "author" : "Author: ",
    "all" : "All",
    "fact" : "Fact Sheets",
    "press" : "Press",
    "factSingle" : "Fact Sheet",
    "pressSingle" : "Press",
    "source" : "link to the source website",
    "only" : "This article is only available in French",
    "sorry" :"Sorry, there are no posts in this category for the moment"
  }
}